[
	{
		"_id": "10000000001",
		"title": "To Kill a Mockingbird",
		"author": "Harper Lee",
		"description": "A novel about the injustices of the American South, seen through the eyes of a young girl.",
		"date_released": "Jul, 1960",
		"file_type": "pdf",
		"language": "English",
		"no_of_pages": 281,
		"cover_img": "https://covers.openlibrary.org/b/id/8225264-L.jpg",
		"isbn": "9780061120084",
		"subjects": ["Fiction", "Classic", "Race Relations"],
		"status": "Available",
		"bookUrl": "https://example.com/tokillamockingbird.pdf"
	},
	{
		"_id": "10000000002",
		"title": "1984",
		"author": "George Orwell",
		"description": "A dystopian novel set in a totalitarian society under constant surveillance.",
		"date_released": "Jun, 1949",
		"file_type": "epub",
		"language": "English",
		"no_of_pages": 328,
		"cover_img": "https://covers.openlibrary.org/b/id/8234567-L.jpg",
		"isbn": "9780451524935",
		"subjects": ["Fiction", "Dystopia", "Political"],
		"status": "Available",
		"bookUrl": "https://example.com/1984.pdf"
	},
	{
		"_id": "10000000003",
		"title": "Pride and Prejudice",
		"author": "Jane Austen",
		"description": "A romantic novel that deals with issues of class, marriage, and morality.",
		"date_released": "Jan, 1813",
		"file_type": "mobi",
		"language": "English",
		"no_of_pages": 279,
		"cover_img": "https://covers.openlibrary.org/b/id/8225236-L.jpg",
		"isbn": "9780141199078",
		"subjects": ["Fiction", "Romance", "Classic"],
		"status": "Available",
		"bookUrl": "https://example.com/prideandprejudice.pdf"
	},
	{
		"_id": "10000000004",
		"title": "The Great Gatsby",
		"author": "F. Scott Fitzgerald",
		"description": "A novel set in the Roaring Twenties, focusing on themes of wealth and the American Dream.",
		"date_released": "Apr, 1925",
		"file_type": "pdf",
		"language": "English",
		"no_of_pages": 180,
		"cover_img": "https://covers.openlibrary.org/b/id/8225544-L.jpg",
		"isbn": "9780743273565",
		"subjects": ["Fiction", "Classic", "Tragedy"],
		"status": "Available",
		"bookUrl": "https://example.com/thegreatgatsby.pdf"
	},
	{
		"_id": "10000000005",
		"title": "Moby Dick",
		"author": "Herman Melville",
		"description": "A novel about a captain's obsessive quest to hunt a giant white whale.",
		"date_released": "Oct, 1851",
		"file_type": "pdf",
		"language": "English",
		"no_of_pages": 635,
		"cover_img": "https://covers.openlibrary.org/b/id/8225144-L.jpg",
		"isbn": "9781503280786",
		"subjects": ["Fiction", "Adventure", "Classic"],
		"status": "Available",
		"bookUrl": "https://example.com/mobydick.pdf"
	},
	{
		"_id": "10000000006",
		"title": "The Catcher in the Rye",
		"author": "J.D. Salinger",
		"description": "A story about teenage alienation and rebellion, narrated by Holden Caulfield.",
		"date_released": "Jul, 1951",
		"file_type": "epub",
		"language": "English",
		"no_of_pages": 277,
		"cover_img": "https://covers.openlibrary.org/b/id/8225565-L.jpg",
		"isbn": "9780316769488",
		"subjects": ["Fiction", "Classic", "Coming-of-Age"],
		"status": "Available",
		"bookUrl": "https://example.com/catcherintherye.pdf"
	},
	{
		"_id": "10000000007",
		"title": "Brave New World",
		"author": "Aldous Huxley",
		"description": "A dystopian novel exploring a future society based on pleasure and control.",
		"date_released": "Nov, 1932",
		"file_type": "pdf",
		"language": "English",
		"no_of_pages": 268,
		"cover_img": "https://covers.openlibrary.org/b/id/8225244-L.jpg",
		"isbn": "9780060850524",
		"subjects": ["Fiction", "Dystopia", "Philosophy"],
		"status": "Available",
		"bookUrl": "https://example.com/bravenewworld.pdf"
	},
	{
		"_id": "10000000008",
		"title": "The Hobbit",
		"author": "J.R.R. Tolkien",
		"description": "A fantasy adventure about a hobbit's journey to reclaim a lost kingdom.",
		"date_released": "Sep, 1937",
		"file_type": "epub",
		"language": "English",
		"no_of_pages": 310,
		"cover_img": "https://covers.openlibrary.org/b/id/8225276-L.jpg",
		"isbn": "9780547928227",
		"subjects": ["Fiction", "Fantasy", "Adventure"],
		"status": "Available",
		"bookUrl": "https://example.com/thehobbit.pdf"
	},
	{
		"_id": "10000000009",
		"title": "War and Peace",
		"author": "Leo Tolstoy",
		"description": "An epic novel about the Napoleonic wars and Russian society.",
		"date_released": "Nov, 1869",
		"file_type": "pdf",
		"language": "English",
		"no_of_pages": 1225,
		"cover_img": "https://covers.openlibrary.org/b/id/8225526-L.jpg",
		"isbn": "9780199232765",
		"subjects": ["Fiction", "Historical", "Epic"],
		"status": "Available",
		"bookUrl": "https://example.com/warandpeace.pdf"
	},
	{
		"_id": "10000000010",
		"title": "Crime and Punishment",
		"author": "Fyodor Dostoevsky",
		"description": "A psychological novel that explores guilt, morality, and redemption.",
		"date_released": "Nov, 1866",
		"file_type": "pdf",
		"language": "English",
		"no_of_pages": 671,
		"cover_img": "https://covers.openlibrary.org/b/id/8225265-L.jpg",
		"isbn": "9780143058144",
		"subjects": ["Fiction", "Philosophy", "Classic"],
		"status": "Available",
		"bookUrl": "https://example.com/crimeandpunishment.pdf"
	},
	{
		"_id": "10000000011",
		"title": "Frankenstein",
		"author": "Mary Shelley",
		"description": "A novel about a scientist's creation of a monster and its tragic consequences.",
		"date_released": "Nov, 1818",
		"file_type": "mobi",
		"language": "English",
		"no_of_pages": 280,
		"cover_img": "https://covers.openlibrary.org/b/id/8225203-L.jpg",
		"isbn": "9780141439471",
		"subjects": ["Fiction", "Science Fiction", "Horror"],
		"status": "Available",
		"bookUrl": "https://example.com/frankenstein.pdf"
	},
	{
		"_id": "10000000012",
		"title": "The Odyssey",
		"author": "Homer",
		"description": "An ancient Greek epic poem about Odysseus' long journey home after the Trojan War.",
		"date_released": "Nov, 800 BC",
		"file_type": "pdf",
		"language": "English",
		"no_of_pages": 541,
		"cover_img": "https://covers.openlibrary.org/b/id/8225121-L.jpg",
		"isbn": "9780140268867",
		"subjects": ["Fiction", "Epic", "Mythology"],
		"status": "Available",
		"bookUrl": "https://example.com/theodyssey.pdf"
	},
	{
		"_id": "10000000013",
		"title": "Dracula",
		"author": "Bram Stoker",
		"description": "A gothic horror novel about Count Dracula and his quest to move from Transylvania to England.",
		"date_released": "Nov, 1897",
		"file_type": "epub",
		"language": "English",
		"no_of_pages": 418,
		"cover_img": "https://covers.openlibrary.org/b/id/8225212-L.jpg",
		"isbn": "9780141439921",
		"subjects": ["Fiction", "Horror", "Gothic"],
		"status": "Available",
		"bookUrl": "https://example.com/dracula.pdf"
	},
	{
		"_id": "10000000014",
		"title": "The Iliad",
		"author": "Homer",
		"description": "An epic poem set during the Trojan War, focusing on the hero Achilles.",
		"date_released": "Nov, 760 BC",
		"file_type": "pdf",
		"language": "English",
		"no_of_pages": 644,
		"cover_img": "https://covers.openlibrary.org/b/id/8225215-L.jpg",
		"isbn": "9780140275360",
		"subjects": ["Fiction", "Epic", "Mythology"],
		"status": "Available",
		"bookUrl": "https://example.com/theiliad.pdf"
	},
	{
		"_id": "10000000015",
		"title": "The Picture of Dorian Gray",
		"author": "Oscar Wilde",
		"description": "A philosophical novel about a man whose portrait ages while he remains young.",
		"date_released": "Nov, 1890",
		"file_type": "epub",
		"language": "English",
		"no_of_pages": 254,
		"cover_img": "https://covers.openlibrary.org/b/id/8225223-L.jpg",
		"isbn": "9780141439570",
		"subjects": ["Fiction", "Philosophy", "Gothic"],
		"status": "Available",
		"bookUrl": "https://example.com/doriangray.pdf"
	},

	{
		"_id": "10000000016",
		"title": "The Lord of the Rings",
		"author": "J.R.R. Tolkien",
		"description": "An epic fantasy trilogy following the quest to destroy the One Ring and defeat Sauron.",
		"date_released": "Jul, 1954",
		"file_type": "pdf",
		"language": "English",
		"no_of_pages": 1216,
		"cover_img": "https://covers.openlibrary.org/b/id/8225277-L.jpg",
		"isbn": "9780618640157",
		"subjects": ["Fiction", "Fantasy", "Adventure"],
		"status": "Available",
		"bookUrl": "https://example.com/thelordoftherings.pdf"
	},
	{
		"_id": "10000000017",
		"title": "Jane Eyre",
		"author": "Charlotte Brontë",
		"description": "A novel that explores themes of morality, religion, and social class through the life of an orphaned girl.",
		"date_released": "Nov, 1847",
		"file_type": "epub",
		"language": "English",
		"no_of_pages": 507,
		"cover_img": "https://covers.openlibrary.org/b/id/8225134-L.jpg",
		"isbn": "9780141441146",
		"subjects": ["Fiction", "Romance", "Classic"],
		"status": "Available",
		"bookUrl": "https://example.com/janeeyre.pdf"
	},
	{
		"_id": "10000000018",
		"title": "The Brothers Karamazov",
		"author": "Fyodor Dostoevsky",
		"description": "A philosophical novel about the moral struggles of the Karamazov family.",
		"date_released": "Nov, 1880",
		"file_type": "pdf",
		"language": "English",
		"no_of_pages": 796,
		"cover_img": "https://covers.openlibrary.org/b/id/8225300-L.jpg",
		"isbn": "9780374528379",
		"subjects": ["Fiction", "Philosophy", "Classic"],
		"status": "Available",
		"bookUrl": "https://example.com/thebrotherskaramazov.pdf"
	},
	{
		"_id": "10000000019",
		"title": "The Divine Comedy",
		"author": "Dante Alighieri",
		"description": "An epic poem that takes the reader through Hell, Purgatory, and Heaven.",
		"date_released": "Nov, 1320",
		"file_type": "pdf",
		"language": "English",
		"no_of_pages": 798,
		"cover_img": "https://covers.openlibrary.org/b/id/8225502-L.jpg",
		"isbn": "9780140448955",
		"subjects": ["Fiction", "Epic", "Philosophy"],
		"status": "Available",
		"bookUrl": "https://example.com/thedivinecomedy.pdf"
	},
	{
		"_id": "10000000020",
		"title": "Wuthering Heights",
		"author": "Emily Brontë",
		"description": "A gothic novel that tells a tale of passion, revenge, and the haunting legacy of love.",
		"date_released": "Nov, 1847",
		"file_type": "epub",
		"language": "English",
		"no_of_pages": 416,
		"cover_img": "https://covers.openlibrary.org/b/id/8225146-L.jpg",
		"isbn": "9780141439556",
		"subjects": ["Fiction", "Romance", "Gothic"],
		"status": "Available",
		"bookUrl": "https://example.com/wutheringheights.pdf"
	},
	{
		"_id": "10000000021",
		"title": "The Count of Monte Cristo",
		"author": "Alexandre Dumas",
		"description": "A classic tale of an innocent man wrongly imprisoned, who escapes and seeks revenge.",
		"date_released": "Nov, 1844",
		"file_type": "pdf",
		"language": "English",
		"no_of_pages": 1276,
		"cover_img": "https://covers.openlibrary.org/b/id/8225227-L.jpg",
		"isbn": "9780140449266",
		"subjects": ["Fiction", "Adventure", "Revenge"],
		"status": "Available",
		"bookUrl": "https://example.com/thecountofmontecristo.pdf"
	},
	{
		"_id": "10000000022",
		"title": "Don Quixote",
		"author": "Miguel de Cervantes",
		"description": "A comic tale about a man who believes he is a knight, embarking on a series of absurd adventures.",
		"date_released": "Nov, 1605",
		"file_type": "epub",
		"language": "English",
		"no_of_pages": 1072,
		"cover_img": "https://covers.openlibrary.org/b/id/8225161-L.jpg",
		"isbn": "9780060934347",
		"subjects": ["Fiction", "Adventure", "Classic"],
		"status": "Available",
		"bookUrl": "https://example.com/donquixote.pdf"
	},
	{
		"_id": "10000000023",
		"title": "Les Misérables",
		"author": "Victor Hugo",
		"description": "An epic novel set in post-revolutionary France, focusing on themes of justice and redemption.",
		"date_released": "Nov, 1862",
		"file_type": "pdf",
		"language": "English",
		"no_of_pages": 1463,
		"cover_img": "https://covers.openlibrary.org/b/id/8225154-L.jpg",
		"isbn": "9780140444308",
		"subjects": ["Fiction", "Historical", "Classic"],
		"status": "Available",
		"bookUrl": "https://example.com/lesmiserables.pdf"
	},
	{
		"_id": "10000000024",
		"title": "Ulysses",
		"author": "James Joyce",
		"description": "A modernist novel that chronicles the experiences of Leopold Bloom in Dublin over the course of a single day.",
		"date_released": "Nov, 1922",
		"file_type": "pdf",
		"language": "English",
		"no_of_pages": 732,
		"cover_img": "https://covers.openlibrary.org/b/id/8225241-L.jpg",
		"isbn": "9780141182803",
		"subjects": ["Fiction", "Modernism", "Classic"],
		"status": "Available",
		"bookUrl": "https://example.com/ulysses.pdf"
	},
	{
		"_id": "10000000025",
		"title": "Anna Karenina",
		"author": "Leo Tolstoy",
		"description": "A novel about love, marriage, and society in 19th-century Russia, focusing on the tragic fate of Anna.",
		"date_released": "Nov, 1877",
		"file_type": "epub",
		"language": "English",
		"no_of_pages": 864,
		"cover_img": "https://covers.openlibrary.org/b/id/8225289-L.jpg",
		"isbn": "9780143035008",
		"subjects": ["Fiction", "Romance", "Classic"],
		"status": "Available",
		"bookUrl": "https://example.com/annakarenina.pdf"
	},

	{
		"_id": "10000000026",
		"title": "War and Peace",
		"author": "Leo Tolstoy",
		"description": "A historical novel that intertwines the lives of five families against the backdrop of the Napoleonic wars.",
		"date_released": "Nov, 1869",
		"file_type": "pdf",
		"language": "English",
		"no_of_pages": 1225,
		"cover_img": "https://covers.openlibrary.org/b/id/8225118-L.jpg",
		"isbn": "9780140447934",
		"subjects": ["Fiction", "Historical", "Classic"],
		"status": "Available",
		"bookUrl": "https://example.com/warandpeace.pdf"
	},
	{
		"_id": "10000000027",
		"title": "Moby-Dick",
		"author": "Herman Melville",
		"description": "A sailor's narrative of the obsessive quest to kill the white whale, Moby Dick.",
		"date_released": "Nov, 1851",
		"file_type": "epub",
		"language": "English",
		"no_of_pages": 720,
		"cover_img": "https://covers.openlibrary.org/b/id/8225179-L.jpg",
		"isbn": "9780142437247",
		"subjects": ["Fiction", "Adventure", "Classic"],
		"status": "Available",
		"bookUrl": "https://example.com/mobydick.pdf"
	},
	{
		"_id": "10000000028",
		"title": "The Catcher in the Rye",
		"author": "J.D. Salinger",
		"description": "A coming-of-age novel about teenage rebellion and disillusionment.",
		"date_released": "Nov, 1951",
		"file_type": "pdf",
		"language": "English",
		"no_of_pages": 277,
		"cover_img": "https://covers.openlibrary.org/b/id/8225194-L.jpg",
		"isbn": "9780316769488",
		"subjects": ["Fiction", "Classic", "Coming-of-Age"],
		"status": "Available",
		"bookUrl": "https://example.com/thecatcherintherye.pdf"
	},
	{
		"_id": "10000000029",
		"title": "Crime and Punishment",
		"author": "Fyodor Dostoevsky",
		"description": "A psychological novel about a young man's moral dilemmas after committing a murder.",
		"date_released": "Nov, 1866",
		"file_type": "epub",
		"language": "English",
		"no_of_pages": 671,
		"cover_img": "https://covers.openlibrary.org/b/id/8225106-L.jpg",
		"isbn": "9780140449136",
		"subjects": ["Fiction", "Philosophy", "Classic"],
		"status": "Available",
		"bookUrl": "https://example.com/crimeandpunishment.pdf"
	},
	{
		"_id": "10000000030",
		"title": "Frankenstein",
		"author": "Mary Shelley",
		"description": "A Gothic novel about a scientist who creates a monster, exploring themes of creation and responsibility.",
		"date_released": "Nov, 1818",
		"file_type": "pdf",
		"language": "English",
		"no_of_pages": 280,
		"cover_img": "https://covers.openlibrary.org/b/id/8225182-L.jpg",
		"isbn": "9780141439471",
		"subjects": ["Fiction", "Horror", "Gothic"],
		"status": "Available",
		"bookUrl": "https://example.com/frankenstein.pdf"
	},
	{
		"_id": "10000000031",
		"title": "The Odyssey",
		"author": "Homer",
		"description": "An epic poem about the adventures of Odysseus as he journeys home after the Trojan War.",
		"date_released": "Nov, 700 BC",
		"file_type": "epub",
		"language": "English",
		"no_of_pages": 560,
		"cover_img": "https://covers.openlibrary.org/b/id/8225232-L.jpg",
		"isbn": "9780140268867",
		"subjects": ["Fiction", "Epic", "Mythology"],
		"status": "Available",
		"bookUrl": "https://example.com/theodyssey.pdf"
	},
	{
		"_id": "10000000032",
		"title": "Brave New World",
		"author": "Aldous Huxley",
		"description": "A dystopian novel set in a future world where technology controls society and individuality is suppressed.",
		"date_released": "Nov, 1932",
		"file_type": "pdf",
		"language": "English",
		"no_of_pages": 311,
		"cover_img": "https://covers.openlibrary.org/b/id/8225261-L.jpg",
		"isbn": "9780060850524",
		"subjects": ["Fiction", "Dystopia", "Science Fiction"],
		"status": "Available",
		"bookUrl": "https://example.com/bravenewworld.pdf"
	},
	{
		"_id": "10000000033",
		"title": "1984",
		"author": "George Orwell",
		"description": "A dystopian novel about a totalitarian regime that uses surveillance and control to maintain power.",
		"date_released": "Nov, 1949",
		"file_type": "epub",
		"language": "English",
		"no_of_pages": 328,
		"cover_img": "https://covers.openlibrary.org/b/id/8225295-L.jpg",
		"isbn": "9780451524935",
		"subjects": ["Fiction", "Dystopia", "Classic"],
		"status": "Available",
		"bookUrl": "https://example.com/1984.pdf"
	},
	{
		"_id": "10000000034",
		"title": "The Hobbit",
		"author": "J.R.R. Tolkien",
		"description": "A fantasy novel following Bilbo Baggins as he embarks on an epic journey to reclaim treasure from a dragon.",
		"date_released": "Nov, 1937",
		"file_type": "pdf",
		"language": "English",
		"no_of_pages": 310,
		"cover_img": "https://covers.openlibrary.org/b/id/8225167-L.jpg",
		"isbn": "9780547928227",
		"subjects": ["Fiction", "Fantasy", "Adventure"],
		"status": "Available",
		"bookUrl": "https://example.com/thehobbit.pdf"
	},
	{
		"_id": "10000000035",
		"title": "A Tale of Two Cities",
		"author": "Charles Dickens",
		"description": "A historical novel set during the French Revolution, exploring themes of sacrifice and resurrection.",
		"date_released": "Nov, 1859",
		"file_type": "epub",
		"language": "English",
		"no_of_pages": 448,
		"cover_img": "https://covers.openlibrary.org/b/id/8225142-L.jpg",
		"isbn": "9780141439600",
		"subjects": ["Fiction", "Historical", "Classic"],
		"status": "Available",
		"bookUrl": "https://example.com/ataleoftwocities.pdf"
	}
]
